{
  "sections": {
    "1655812594c73339b9": {
      "type": "custom-image-banner",
      "settings": {
        "title": "Des vins vivants, respectueux de la nature"
      }
    },
    "1655915878d77c4479": {
      "type": "custom-latest-products",
      "settings": {
        "title": "Nos vins du moment",
        "collection": "cave-exclusive",
        "productLength": 4
      }
    },
    "1655816049054385d1": {
      "type": "custom-bottles-pack",
      "settings": {
      }
    },
    "1655890697a5d50126": {
      "type": "custom-text-banner",
      "settings": {
      }
    },
    "16559027566fb828bc": {
      "type": "custom-latest-articles",
      "settings": {
      }
    },
    "16558172108cf648ab": {
      "type": "custom-newsletter",
      "settings": {
      }
    }
  },
  "order": [
    "1655812594c73339b9",
    "1655915878d77c4479",
    "1655816049054385d1",
    "1655890697a5d50126",
    "16559027566fb828bc",
    "16558172108cf648ab"
  ]
}
